{
    "query_stream_1_query_1": "0:00:02.976671",
    "query_stream_1_query_10": "0:00:00.551809",
    "query_stream_1_query_11": "0:00:00.114502",
    "query_stream_1_query_12": "0:00:00.840444",
    "query_stream_1_query_13": "0:00:01.138920",
    "query_stream_1_query_14": "0:00:00.507787",
    "query_stream_1_query_15": "0:00:10.269535",
    "query_stream_1_query_16": "0:00:00.907760",
    "query_stream_1_query_17": "0:00:03.236507",
    "query_stream_1_query_18": "0:00:03.944014",
    "query_stream_1_query_19": "0:00:00.054298",
    "query_stream_1_query_2": "0:00:00.409099",
    "query_stream_1_query_20": "0:00:02.163986",
    "query_stream_1_query_21": "0:00:01.180471",
    "query_stream_1_query_22": "0:00:00.147901",
    "query_stream_1_query_3": "0:00:00.681767",
    "query_stream_1_query_4": "0:00:00.198119",
    "query_stream_1_query_5": "0:00:00.323043",
    "query_stream_1_query_6": "0:00:00.574223",
    "query_stream_1_query_7": "0:00:00.385003",
    "query_stream_1_query_8": "0:00:00.176650",
    "query_stream_1_query_9": "0:00:01.088350"
}